.gitignore
AUTHORS
CHANGELOG.md
LICENSE
MANIFEST.in
README.rst
pyproject.toml
pytest.ini
setup.cfg
setup.py
.github/workflows/flake8.yml
.github/workflows/publish.yml
.github/workflows/test.yml
frontend/ContactMechanicsCard.vue
frontend/ContactMechanicsParametersModal.vue
frontend/contact_mechanics_card.js
topobank_contact/__init__.py
topobank_contact/apps.py
topobank_contact/downloads.py
topobank_contact/functions.py
topobank_contact/signals.py
topobank_contact/urls.py
topobank_contact/views.py
topobank_contact.egg-info/PKG-INFO
topobank_contact.egg-info/SOURCES.txt
topobank_contact.egg-info/dependency_links.txt
topobank_contact.egg-info/entry_points.txt
topobank_contact.egg-info/requires.txt
topobank_contact.egg-info/top_level.txt
topobank_contact/migrations/__init__.py
topobank_contact/tests/__init__.py
topobank_contact/tests/conftest.py
topobank_contact/tests/test_api.py
topobank_contact/tests/test_downloads.py
topobank_contact/tests/test_functions.py
topobank_contact/tests/test_views.py
topobank_contact/tests/urls.py